{
  "allowedblocks": [
    {
      "name": "movement",
      "blocks": 
      [
        {
          "function": "movement-right"
        },
        {
          "function": "movement-left"
        },
        {
          "function": "movement-jump"
        },
        {
          "function": "movement-up"
        },
        {
          "function": "movement-down"
        }
      ]
    }
  ],
  "itemsVertical":
  [
    {
      "itemsHorizontal": [0,0,0,0,0,0,0,0]
    },
    {
      "itemsHorizontal": [0,0,0,0,3,0,0,0]
    },
    {
      "itemsHorizontal": [0,0,0,4,2,4,0,0]
    },
    {
      "itemsHorizontal": [1,2,0,3,2,0,3,0]
    }
  ],
  "characterFacing": "right"
}